pyfeltor/__init__.py
pyfeltor/dg/__init__.py
pyfeltor/dg/enums.py
pyfeltor/dg/evaluation.py
pyfeltor/dg/grid.py
pyfeltor/dg/create/__init__.py
pyfeltor/dg/create/derivative.py
pyfeltor/dg/create/dx.py
pyfeltor/dg/create/elliptic.py
pyfeltor/dg/create/interpolation.py
pyfeltor/dg/create/operators.py
pyfeltor/dg/create/weights.py
pyfeltor/dg/geo/__init__.py
pyfeltor/dg/geo/circular.cpp
pyfeltor/dg/geo/circular.cpython-312-x86_64-linux-gnu.so
pyfeltor/dg/geo/flux.cpp
pyfeltor/dg/geo/flux.cpython-312-x86_64-linux-gnu.so
pyfeltor/dg/geo/geometries.cpp
pyfeltor/dg/geo/geometries.cpython-312-x86_64-linux-gnu.so
pyfeltor/dg/geo/guenter.cpp
pyfeltor/dg/geo/guenter.cpython-312-x86_64-linux-gnu.so
pyfeltor/dg/geo/mod.cpp
pyfeltor/dg/geo/mod.cpython-312-x86_64-linux-gnu.so
pyfeltor/dg/geo/polynomial.cpp
pyfeltor/dg/geo/polynomial.cpython-312-x86_64-linux-gnu.so
pyfeltor/dg/geo/solovev.cpp
pyfeltor/dg/geo/solovev.cpython-312-x86_64-linux-gnu.so
pyfeltor/dg/geo/toroidal.cpp
pyfeltor/dg/geo/toroidal.cpython-312-x86_64-linux-gnu.so
pyfeltor/dg/geo/utility.cpp
pyfeltor/dg/geo/utility.cpython-312-x86_64-linux-gnu.so
pyfeltor-0.1.1.dist-info/METADATA
pyfeltor-0.1.1.dist-info/WHEEL
pyfeltor-0.1.1.dist-info/RECORD
pyfeltor-0.1.1.dist-info/licenses/LICENSE
