Metadata-Version: 2.2
Name: pyfeltor
Version: 0.1.1
Summary: A subset of Feltor's dg library as a python implementation
Author-Email: Matthias Wiesenberger <mattwi@dtu.dk>
License: MIT License
Classifier: Intended Audience :: Science/Research
Classifier: Intended Audience :: Education
Classifier: Intended Audience :: Developers
Classifier: Natural Language :: English
Classifier: Operating System :: POSIX :: Linux
Classifier: Programming Language :: Python :: 3
Project-URL: Source, https://github.com/feltor-dev/pyfeltor
Project-URL: Tracker, https://github.com/feltor-dev/pyfeltor/issues
Requires-Python: >=3.12
Requires-Dist: scipy>=1.10.0
Requires-Dist: numpy>=1.24.0
Provides-Extra: test
Requires-Dist: pytest; extra == "test"
Requires-Dist: pytest-datadir; extra == "test"
Provides-Extra: lint
Requires-Dist: ruff; extra == "lint"
